sprinkl_async/__init__.py
sprinkl_async/__version__.py
sprinkl_async/authtoken.py
sprinkl_async/client.py
sprinkl_async/const.py
sprinkl_async/controller.py
sprinkl_async/dataobject.py
sprinkl_async/errors.py
sprinkl_async/moisturesensor.py
sprinkl_async/moisturesensors.py
sprinkl_async/pageobject.py
sprinkl_async/schedule.py
sprinkl_async/schedules.py
sprinkl_async/webhook.py
sprinkl_async/webhook_objects.py
sprinkl_async/webhooks.py
sprinkl_async/zone.py
sprinkl_async/zones.py
tests/fixtures/__init__.py
sprinkl_async-0.1.2.dist-info/AUTHORS.md
sprinkl_async-0.1.2.dist-info/LICENSE
sprinkl_async-0.1.2.dist-info/METADATA
sprinkl_async-0.1.2.dist-info/WHEEL
sprinkl_async-0.1.2.dist-info/top_level.txt
sprinkl_async-0.1.2.dist-info/RECORD
