Metadata-Version: 2.1
Name: sprinkl-async
Version: 0.1.2
Summary: API for Sprinkl sprinkler controller
Home-page: https://github.com/ptorsten/sprinkl-async
Author: Patrik Torstensson
Author-email: patrik.torstensson@gmail.com
License: Apache
Platform: UNKNOWN
Classifier: License :: OSI Approved :: Apache Software License
Classifier: Framework :: AsyncIO
Classifier: Programming Language :: Python
Classifier: Programming Language :: Python :: 3
Classifier: Programming Language :: Python :: 3.5
Classifier: Programming Language :: Python :: 3.6
Classifier: Programming Language :: Python :: 3.7
Classifier: Programming Language :: Python :: Implementation :: CPython
Classifier: Programming Language :: Python :: Implementation :: PyPy
Requires-Python: >=3.5.3
Requires-Dist: aiohttp
